tplinkrouter/__init__.py
tplinkrouter-1.0.0.dist-info/LICENSE
tplinkrouter-1.0.0.dist-info/METADATA
tplinkrouter-1.0.0.dist-info/WHEEL
tplinkrouter-1.0.0.dist-info/top_level.txt
tplinkrouter-1.0.0.dist-info/RECORD
