Metadata-Version: 2.1
Name: tplinkrouter
Version: 1.0.0
Summary: TP-Link Archer C50 API
Home-page: https://github.com/menahishayan/TP-Link-Archer-C50-API
Author: Menahi Shayan
Author-email: menahi.shayan@gmail.com
License: UNKNOWN
Platform: UNKNOWN
Classifier: Programming Language :: Python :: 3
Classifier: License :: OSI Approved :: GNU General Public License v3 or later (GPLv3+)
Classifier: Operating System :: OS Independent
Requires-Python: >=3.7
